raysecretsproxy/__init__.py
raysecretsproxy/aws_secret_operator.py
raysecretsproxy/gcp_secret_operator.py
raysecretsproxy/ray_secret.py
raysecretsproxy/ray_secret_operator.py
raysecretsproxy/ray_secret_proxy.py
raysecretsproxy-0.0.3.dist-info/LICENSE
raysecretsproxy-0.0.3.dist-info/METADATA
raysecretsproxy-0.0.3.dist-info/WHEEL
raysecretsproxy-0.0.3.dist-info/top_level.txt
raysecretsproxy-0.0.3.dist-info/RECORD
