Metadata-Version: 2.1
Name: raysecretsproxy
Version: 0.0.3
Summary: A Ray native mechanism of interacting with cloud-provider secrets management.
Author-email: Dominic Catalano <dominic@anyscale.com>, Ian Rodney <ilr@anyscale.com>
License: Apache License
Project-URL: Home Page, https://github.com/anyscale/ray-secrets-proxy
Classifier: Programming Language :: Python :: 3
Classifier: Operating System :: OS Independent
License-File: LICENSE
Requires-Dist: cryptography
Requires-Dist: ray
Requires-Dist: boto3
Requires-Dist: google-cloud-secret-manager
